[
  {
    "id": "asset_000",
    "title": "The Ritual of Namaste \u2014 Body Cream (EMAIL / NL)",
    "body": "Immerse yourself in the The Ritual of Namaste experience. Our Body Cream is crafted to transform your daily routine into a mindful ritual.",
    "asset_type": "email",
    "collection": "The Ritual of Namaste",
    "product": "Body Cream",
    "ritual_occasion": "self-care",
    "audience": "loyalty",
    "channel": "email",
    "market": "NL",
    "language": "nl",
    "approval_status": "approved",
    "master_asset_id": null,
    "performance_tag": "high",
    "tone": "luxury"
  },
  {
    "id": "asset_001",
    "title": "The Ritual of Sakura \u2014 Shower Foam (LANDING / DE)",
    "body": "The Shower Foam from The Ritual of Sakura invites you to slow down, breathe deeply, and embrace the art of self-care.",
    "asset_type": "landing",
    "collection": "The Ritual of Sakura",
    "product": "Shower Foam",
    "ritual_occasion": "gifting",
    "audience": "new",
    "channel": "landing",
    "market": "DE",
    "language": "de",
    "approval_status": "approved",
    "master_asset_id": null,
    "performance_tag": "high",
    "tone": "warm"
  },
  {
    "id": "asset_002",
    "title": "The Ritual of Ayurveda \u2014 Face Oil (SOCIAL / UK)",
    "body": "Rediscover balance with The Ritual of Ayurveda. The Face Oil is inspired by ancient wisdom and crafted for modern life.",
    "asset_type": "social",
    "collection": "The Ritual of Ayurveda",
    "product": "Face Oil",
    "ritual_occasion": "replenishment",
    "audience": "reactivation",
    "channel": "social",
    "market": "UK",
    "language": "en",
    "approval_status": "approved",
    "master_asset_id": null,
    "performance_tag": "medium",
    "tone": "informative"
  },
  {
    "id": "asset_003",
    "title": "The Ritual of Namaste \u2014 Bath Salt (ALL / all)",
    "body": "Give the gift of ritual. The The Ritual of Namaste Bath Salt makes every moment a celebration of calm and beauty.",
    "asset_type": "email",
    "collection": "The Ritual of Namaste",
    "product": "Bath Salt",
    "ritual_occasion": "self-care",
    "audience": "all",
    "channel": "all",
    "market": "all",
    "language": "en",
    "approval_status": "pending",
    "master_asset_id": null,
    "performance_tag": "low",
    "tone": "luxury"
  },
  {
    "id": "asset_004",
    "title": "The Ritual of Sakura \u2014 Candle (EMAIL / NL)",
    "body": "Your skin deserves the best. The Candle from The Ritual of Sakura is formulated with natural ingredients for a luxurious daily ritual.",
    "asset_type": "email",
    "collection": "The Ritual of Sakura",
    "product": "Candle",
    "ritual_occasion": "gifting",
    "audience": "loyalty",
    "channel": "email",
    "market": "NL",
    "language": "nl",
    "approval_status": "expired",
    "master_asset_id": null,
    "performance_tag": "high",
    "tone": "warm"
  },
  {
    "id": "asset_005",
    "title": "The Ritual of Ayurveda \u2014 Body Cream (LANDING / DE)",
    "body": "Immerse yourself in the The Ritual of Ayurveda experience. Our Body Cream is crafted to transform your daily routine into a mindful ritual.",
    "asset_type": "landing",
    "collection": "The Ritual of Ayurveda",
    "product": "Body Cream",
    "ritual_occasion": "replenishment",
    "audience": "new",
    "channel": "landing",
    "market": "DE",
    "language": "de",
    "approval_status": "approved",
    "master_asset_id": null,
    "performance_tag": "high",
    "tone": "informative"
  },
  {
    "id": "asset_006",
    "title": "The Ritual of Namaste \u2014 Shower Foam (SOCIAL / UK)",
    "body": "The Shower Foam from The Ritual of Namaste invites you to slow down, breathe deeply, and embrace the art of self-care.",
    "asset_type": "social",
    "collection": "The Ritual of Namaste",
    "product": "Shower Foam",
    "ritual_occasion": "self-care",
    "audience": "reactivation",
    "channel": "social",
    "market": "UK",
    "language": "en",
    "approval_status": "approved",
    "master_asset_id": "asset_005",
    "performance_tag": "medium",
    "tone": "luxury"
  },
  {
    "id": "asset_007",
    "title": "The Ritual of Sakura \u2014 Face Oil (ALL / all)",
    "body": "Rediscover balance with The Ritual of Sakura. The Face Oil is inspired by ancient wisdom and crafted for modern life.",
    "asset_type": "email",
    "collection": "The Ritual of Sakura",
    "product": "Face Oil",
    "ritual_occasion": "gifting",
    "audience": "all",
    "channel": "all",
    "market": "all",
    "language": "en",
    "approval_status": "approved",
    "master_asset_id": "asset_005",
    "performance_tag": "low",
    "tone": "warm"
  },
  {
    "id": "asset_008",
    "title": "The Ritual of Ayurveda \u2014 Bath Salt (EMAIL / NL)",
    "body": "Give the gift of ritual. The The Ritual of Ayurveda Bath Salt makes every moment a celebration of calm and beauty.",
    "asset_type": "email",
    "collection": "The Ritual of Ayurveda",
    "product": "Bath Salt",
    "ritual_occasion": "replenishment",
    "audience": "loyalty",
    "channel": "email",
    "market": "NL",
    "language": "nl",
    "approval_status": "pending",
    "master_asset_id": "asset_005",
    "performance_tag": "high",
    "tone": "informative"
  },
  {
    "id": "asset_009",
    "title": "The Ritual of Namaste \u2014 Candle (LANDING / DE)",
    "body": "Your skin deserves the best. The Candle from The Ritual of Namaste is formulated with natural ingredients for a luxurious daily ritual.",
    "asset_type": "landing",
    "collection": "The Ritual of Namaste",
    "product": "Candle",
    "ritual_occasion": "self-care",
    "audience": "new",
    "channel": "landing",
    "market": "DE",
    "language": "de",
    "approval_status": "expired",
    "master_asset_id": "asset_005",
    "performance_tag": "high",
    "tone": "luxury"
  },
  {
    "id": "asset_010",
    "title": "The Ritual of Sakura \u2014 Body Cream (SOCIAL / UK)",
    "body": "Immerse yourself in the The Ritual of Sakura experience. Our Body Cream is crafted to transform your daily routine into a mindful ritual.",
    "asset_type": "social",
    "collection": "The Ritual of Sakura",
    "product": "Body Cream",
    "ritual_occasion": "gifting",
    "audience": "reactivation",
    "channel": "social",
    "market": "UK",
    "language": "en",
    "approval_status": "approved",
    "master_asset_id": null,
    "performance_tag": "medium",
    "tone": "warm"
  },
  {
    "id": "asset_011",
    "title": "The Ritual of Ayurveda \u2014 Shower Foam (ALL / all)",
    "body": "The Shower Foam from The Ritual of Ayurveda invites you to slow down, breathe deeply, and embrace the art of self-care.",
    "asset_type": "email",
    "collection": "The Ritual of Ayurveda",
    "product": "Shower Foam",
    "ritual_occasion": "replenishment",
    "audience": "all",
    "channel": "all",
    "market": "all",
    "language": "en",
    "approval_status": "approved",
    "master_asset_id": "asset_010",
    "performance_tag": "low",
    "tone": "informative"
  },
  {
    "id": "asset_012",
    "title": "The Ritual of Namaste \u2014 Face Oil (EMAIL / NL)",
    "body": "Rediscover balance with The Ritual of Namaste. The Face Oil is inspired by ancient wisdom and crafted for modern life.",
    "asset_type": "email",
    "collection": "The Ritual of Namaste",
    "product": "Face Oil",
    "ritual_occasion": "self-care",
    "audience": "loyalty",
    "channel": "email",
    "market": "NL",
    "language": "nl",
    "approval_status": "approved",
    "master_asset_id": "asset_010",
    "performance_tag": "high",
    "tone": "luxury"
  },
  {
    "id": "asset_013",
    "title": "The Ritual of Sakura \u2014 Bath Salt (LANDING / DE)",
    "body": "Give the gift of ritual. The The Ritual of Sakura Bath Salt makes every moment a celebration of calm and beauty.",
    "asset_type": "landing",
    "collection": "The Ritual of Sakura",
    "product": "Bath Salt",
    "ritual_occasion": "gifting",
    "audience": "new",
    "channel": "landing",
    "market": "DE",
    "language": "de",
    "approval_status": "pending",
    "master_asset_id": "asset_010",
    "performance_tag": "high",
    "tone": "warm"
  },
  {
    "id": "asset_014",
    "title": "The Ritual of Ayurveda \u2014 Candle (SOCIAL / UK)",
    "body": "Your skin deserves the best. The Candle from The Ritual of Ayurveda is formulated with natural ingredients for a luxurious daily ritual.",
    "asset_type": "social",
    "collection": "The Ritual of Ayurveda",
    "product": "Candle",
    "ritual_occasion": "replenishment",
    "audience": "reactivation",
    "channel": "social",
    "market": "UK",
    "language": "en",
    "approval_status": "expired",
    "master_asset_id": "asset_010",
    "performance_tag": "medium",
    "tone": "informative"
  },
  {
    "id": "asset_015",
    "title": "The Ritual of Namaste \u2014 Body Cream (ALL / all)",
    "body": "Immerse yourself in the The Ritual of Namaste experience. Our Body Cream is crafted to transform your daily routine into a mindful ritual.",
    "asset_type": "email",
    "collection": "The Ritual of Namaste",
    "product": "Body Cream",
    "ritual_occasion": "self-care",
    "audience": "all",
    "channel": "all",
    "market": "all",
    "language": "en",
    "approval_status": "approved",
    "master_asset_id": null,
    "performance_tag": "low",
    "tone": "luxury"
  },
  {
    "id": "asset_016",
    "title": "The Ritual of Sakura \u2014 Shower Foam (EMAIL / NL)",
    "body": "The Shower Foam from The Ritual of Sakura invites you to slow down, breathe deeply, and embrace the art of self-care.",
    "asset_type": "email",
    "collection": "The Ritual of Sakura",
    "product": "Shower Foam",
    "ritual_occasion": "gifting",
    "audience": "loyalty",
    "channel": "email",
    "market": "NL",
    "language": "nl",
    "approval_status": "approved",
    "master_asset_id": "asset_015",
    "performance_tag": "high",
    "tone": "warm"
  },
  {
    "id": "asset_017",
    "title": "The Ritual of Ayurveda \u2014 Face Oil (LANDING / DE)",
    "body": "Rediscover balance with The Ritual of Ayurveda. The Face Oil is inspired by ancient wisdom and crafted for modern life.",
    "asset_type": "landing",
    "collection": "The Ritual of Ayurveda",
    "product": "Face Oil",
    "ritual_occasion": "replenishment",
    "audience": "new",
    "channel": "landing",
    "market": "DE",
    "language": "de",
    "approval_status": "approved",
    "master_asset_id": "asset_015",
    "performance_tag": "high",
    "tone": "informative"
  },
  {
    "id": "asset_018",
    "title": "The Ritual of Namaste \u2014 Bath Salt (SOCIAL / UK)",
    "body": "Give the gift of ritual. The The Ritual of Namaste Bath Salt makes every moment a celebration of calm and beauty.",
    "asset_type": "social",
    "collection": "The Ritual of Namaste",
    "product": "Bath Salt",
    "ritual_occasion": "self-care",
    "audience": "reactivation",
    "channel": "social",
    "market": "UK",
    "language": "en",
    "approval_status": "pending",
    "master_asset_id": "asset_015",
    "performance_tag": "medium",
    "tone": "luxury"
  },
  {
    "id": "asset_019",
    "title": "The Ritual of Sakura \u2014 Candle (ALL / all)",
    "body": "Your skin deserves the best. The Candle from The Ritual of Sakura is formulated with natural ingredients for a luxurious daily ritual.",
    "asset_type": "email",
    "collection": "The Ritual of Sakura",
    "product": "Candle",
    "ritual_occasion": "gifting",
    "audience": "all",
    "channel": "all",
    "market": "all",
    "language": "en",
    "approval_status": "expired",
    "master_asset_id": "asset_015",
    "performance_tag": "low",
    "tone": "warm"
  },
  {
    "id": "asset_020",
    "title": "The Ritual of Ayurveda \u2014 Body Cream (EMAIL / NL)",
    "body": "Immerse yourself in the The Ritual of Ayurveda experience. Our Body Cream is crafted to transform your daily routine into a mindful ritual.",
    "asset_type": "email",
    "collection": "The Ritual of Ayurveda",
    "product": "Body Cream",
    "ritual_occasion": "replenishment",
    "audience": "loyalty",
    "channel": "email",
    "market": "NL",
    "language": "nl",
    "approval_status": "approved",
    "master_asset_id": null,
    "performance_tag": "high",
    "tone": "informative"
  },
  {
    "id": "asset_021",
    "title": "The Ritual of Namaste \u2014 Shower Foam (LANDING / DE)",
    "body": "The Shower Foam from The Ritual of Namaste invites you to slow down, breathe deeply, and embrace the art of self-care.",
    "asset_type": "landing",
    "collection": "The Ritual of Namaste",
    "product": "Shower Foam",
    "ritual_occasion": "self-care",
    "audience": "new",
    "channel": "landing",
    "market": "DE",
    "language": "de",
    "approval_status": "approved",
    "master_asset_id": "asset_020",
    "performance_tag": "high",
    "tone": "luxury"
  },
  {
    "id": "asset_022",
    "title": "The Ritual of Sakura \u2014 Face Oil (SOCIAL / UK)",
    "body": "Rediscover balance with The Ritual of Sakura. The Face Oil is inspired by ancient wisdom and crafted for modern life.",
    "asset_type": "social",
    "collection": "The Ritual of Sakura",
    "product": "Face Oil",
    "ritual_occasion": "gifting",
    "audience": "reactivation",
    "channel": "social",
    "market": "UK",
    "language": "en",
    "approval_status": "approved",
    "master_asset_id": "asset_020",
    "performance_tag": "medium",
    "tone": "warm"
  },
  {
    "id": "asset_023",
    "title": "The Ritual of Ayurveda \u2014 Bath Salt (ALL / all)",
    "body": "Give the gift of ritual. The The Ritual of Ayurveda Bath Salt makes every moment a celebration of calm and beauty.",
    "asset_type": "email",
    "collection": "The Ritual of Ayurveda",
    "product": "Bath Salt",
    "ritual_occasion": "replenishment",
    "audience": "all",
    "channel": "all",
    "market": "all",
    "language": "en",
    "approval_status": "pending",
    "master_asset_id": "asset_020",
    "performance_tag": "low",
    "tone": "informative"
  },
  {
    "id": "asset_024",
    "title": "The Ritual of Namaste \u2014 Candle (EMAIL / NL)",
    "body": "Your skin deserves the best. The Candle from The Ritual of Namaste is formulated with natural ingredients for a luxurious daily ritual.",
    "asset_type": "email",
    "collection": "The Ritual of Namaste",
    "product": "Candle",
    "ritual_occasion": "self-care",
    "audience": "loyalty",
    "channel": "email",
    "market": "NL",
    "language": "nl",
    "approval_status": "expired",
    "master_asset_id": "asset_020",
    "performance_tag": "high",
    "tone": "luxury"
  },
  {
    "id": "asset_025",
    "title": "The Ritual of Sakura \u2014 Body Cream (LANDING / DE)",
    "body": "Immerse yourself in the The Ritual of Sakura experience. Our Body Cream is crafted to transform your daily routine into a mindful ritual.",
    "asset_type": "landing",
    "collection": "The Ritual of Sakura",
    "product": "Body Cream",
    "ritual_occasion": "gifting",
    "audience": "new",
    "channel": "landing",
    "market": "DE",
    "language": "de",
    "approval_status": "approved",
    "master_asset_id": null,
    "performance_tag": "high",
    "tone": "warm"
  },
  {
    "id": "asset_026",
    "title": "The Ritual of Ayurveda \u2014 Shower Foam (SOCIAL / UK)",
    "body": "The Shower Foam from The Ritual of Ayurveda invites you to slow down, breathe deeply, and embrace the art of self-care.",
    "asset_type": "social",
    "collection": "The Ritual of Ayurveda",
    "product": "Shower Foam",
    "ritual_occasion": "replenishment",
    "audience": "reactivation",
    "channel": "social",
    "market": "UK",
    "language": "en",
    "approval_status": "approved",
    "master_asset_id": "asset_025",
    "performance_tag": "medium",
    "tone": "informative"
  },
  {
    "id": "asset_027",
    "title": "The Ritual of Namaste \u2014 Face Oil (ALL / all)",
    "body": "Rediscover balance with The Ritual of Namaste. The Face Oil is inspired by ancient wisdom and crafted for modern life.",
    "asset_type": "email",
    "collection": "The Ritual of Namaste",
    "product": "Face Oil",
    "ritual_occasion": "self-care",
    "audience": "all",
    "channel": "all",
    "market": "all",
    "language": "en",
    "approval_status": "approved",
    "master_asset_id": "asset_025",
    "performance_tag": "low",
    "tone": "luxury"
  },
  {
    "id": "asset_028",
    "title": "The Ritual of Sakura \u2014 Bath Salt (EMAIL / NL)",
    "body": "Give the gift of ritual. The The Ritual of Sakura Bath Salt makes every moment a celebration of calm and beauty.",
    "asset_type": "email",
    "collection": "The Ritual of Sakura",
    "product": "Bath Salt",
    "ritual_occasion": "gifting",
    "audience": "loyalty",
    "channel": "email",
    "market": "NL",
    "language": "nl",
    "approval_status": "pending",
    "master_asset_id": "asset_025",
    "performance_tag": "high",
    "tone": "warm"
  },
  {
    "id": "asset_029",
    "title": "The Ritual of Ayurveda \u2014 Candle (LANDING / DE)",
    "body": "Your skin deserves the best. The Candle from The Ritual of Ayurveda is formulated with natural ingredients for a luxurious daily ritual.",
    "asset_type": "landing",
    "collection": "The Ritual of Ayurveda",
    "product": "Candle",
    "ritual_occasion": "replenishment",
    "audience": "new",
    "channel": "landing",
    "market": "DE",
    "language": "de",
    "approval_status": "expired",
    "master_asset_id": "asset_025",
    "performance_tag": "high",
    "tone": "informative"
  },
  {
    "id": "asset_030",
    "title": "The Ritual of Namaste \u2014 Body Cream (SOCIAL / UK)",
    "body": "Immerse yourself in the The Ritual of Namaste experience. Our Body Cream is crafted to transform your daily routine into a mindful ritual.",
    "asset_type": "social",
    "collection": "The Ritual of Namaste",
    "product": "Body Cream",
    "ritual_occasion": "self-care",
    "audience": "reactivation",
    "channel": "social",
    "market": "UK",
    "language": "en",
    "approval_status": "approved",
    "master_asset_id": null,
    "performance_tag": "medium",
    "tone": "luxury"
  },
  {
    "id": "asset_031",
    "title": "The Ritual of Sakura \u2014 Shower Foam (ALL / all)",
    "body": "The Shower Foam from The Ritual of Sakura invites you to slow down, breathe deeply, and embrace the art of self-care.",
    "asset_type": "email",
    "collection": "The Ritual of Sakura",
    "product": "Shower Foam",
    "ritual_occasion": "gifting",
    "audience": "all",
    "channel": "all",
    "market": "all",
    "language": "en",
    "approval_status": "approved",
    "master_asset_id": "asset_030",
    "performance_tag": "low",
    "tone": "warm"
  },
  {
    "id": "asset_032",
    "title": "The Ritual of Ayurveda \u2014 Face Oil (EMAIL / NL)",
    "body": "Rediscover balance with The Ritual of Ayurveda. The Face Oil is inspired by ancient wisdom and crafted for modern life.",
    "asset_type": "email",
    "collection": "The Ritual of Ayurveda",
    "product": "Face Oil",
    "ritual_occasion": "replenishment",
    "audience": "loyalty",
    "channel": "email",
    "market": "NL",
    "language": "nl",
    "approval_status": "approved",
    "master_asset_id": "asset_030",
    "performance_tag": "high",
    "tone": "informative"
  },
  {
    "id": "asset_033",
    "title": "The Ritual of Namaste \u2014 Bath Salt (LANDING / DE)",
    "body": "Give the gift of ritual. The The Ritual of Namaste Bath Salt makes every moment a celebration of calm and beauty.",
    "asset_type": "landing",
    "collection": "The Ritual of Namaste",
    "product": "Bath Salt",
    "ritual_occasion": "self-care",
    "audience": "new",
    "channel": "landing",
    "market": "DE",
    "language": "de",
    "approval_status": "pending",
    "master_asset_id": "asset_030",
    "performance_tag": "high",
    "tone": "luxury"
  },
  {
    "id": "asset_034",
    "title": "The Ritual of Sakura \u2014 Candle (SOCIAL / UK)",
    "body": "Your skin deserves the best. The Candle from The Ritual of Sakura is formulated with natural ingredients for a luxurious daily ritual.",
    "asset_type": "social",
    "collection": "The Ritual of Sakura",
    "product": "Candle",
    "ritual_occasion": "gifting",
    "audience": "reactivation",
    "channel": "social",
    "market": "UK",
    "language": "en",
    "approval_status": "expired",
    "master_asset_id": "asset_030",
    "performance_tag": "medium",
    "tone": "warm"
  },
  {
    "id": "asset_035",
    "title": "The Ritual of Ayurveda \u2014 Body Cream (ALL / all)",
    "body": "Immerse yourself in the The Ritual of Ayurveda experience. Our Body Cream is crafted to transform your daily routine into a mindful ritual.",
    "asset_type": "email",
    "collection": "The Ritual of Ayurveda",
    "product": "Body Cream",
    "ritual_occasion": "replenishment",
    "audience": "all",
    "channel": "all",
    "market": "all",
    "language": "en",
    "approval_status": "approved",
    "master_asset_id": null,
    "performance_tag": "low",
    "tone": "informative"
  },
  {
    "id": "asset_036",
    "title": "The Ritual of Namaste \u2014 Shower Foam (EMAIL / NL)",
    "body": "The Shower Foam from The Ritual of Namaste invites you to slow down, breathe deeply, and embrace the art of self-care.",
    "asset_type": "email",
    "collection": "The Ritual of Namaste",
    "product": "Shower Foam",
    "ritual_occasion": "self-care",
    "audience": "loyalty",
    "channel": "email",
    "market": "NL",
    "language": "nl",
    "approval_status": "approved",
    "master_asset_id": "asset_035",
    "performance_tag": "high",
    "tone": "luxury"
  },
  {
    "id": "asset_037",
    "title": "The Ritual of Sakura \u2014 Face Oil (LANDING / DE)",
    "body": "Rediscover balance with The Ritual of Sakura. The Face Oil is inspired by ancient wisdom and crafted for modern life.",
    "asset_type": "landing",
    "collection": "The Ritual of Sakura",
    "product": "Face Oil",
    "ritual_occasion": "gifting",
    "audience": "new",
    "channel": "landing",
    "market": "DE",
    "language": "de",
    "approval_status": "approved",
    "master_asset_id": "asset_035",
    "performance_tag": "high",
    "tone": "warm"
  },
  {
    "id": "asset_038",
    "title": "The Ritual of Ayurveda \u2014 Bath Salt (SOCIAL / UK)",
    "body": "Give the gift of ritual. The The Ritual of Ayurveda Bath Salt makes every moment a celebration of calm and beauty.",
    "asset_type": "social",
    "collection": "The Ritual of Ayurveda",
    "product": "Bath Salt",
    "ritual_occasion": "replenishment",
    "audience": "reactivation",
    "channel": "social",
    "market": "UK",
    "language": "en",
    "approval_status": "pending",
    "master_asset_id": "asset_035",
    "performance_tag": "medium",
    "tone": "informative"
  },
  {
    "id": "asset_039",
    "title": "The Ritual of Namaste \u2014 Candle (ALL / all)",
    "body": "Your skin deserves the best. The Candle from The Ritual of Namaste is formulated with natural ingredients for a luxurious daily ritual.",
    "asset_type": "email",
    "collection": "The Ritual of Namaste",
    "product": "Candle",
    "ritual_occasion": "self-care",
    "audience": "all",
    "channel": "all",
    "market": "all",
    "language": "en",
    "approval_status": "expired",
    "master_asset_id": "asset_035",
    "performance_tag": "low",
    "tone": "luxury"
  },
  {
    "id": "asset_040",
    "title": "The Ritual of Sakura \u2014 Body Cream (EMAIL / NL)",
    "body": "Immerse yourself in the The Ritual of Sakura experience. Our Body Cream is crafted to transform your daily routine into a mindful ritual.",
    "asset_type": "email",
    "collection": "The Ritual of Sakura",
    "product": "Body Cream",
    "ritual_occasion": "gifting",
    "audience": "loyalty",
    "channel": "email",
    "market": "NL",
    "language": "nl",
    "approval_status": "approved",
    "master_asset_id": null,
    "performance_tag": "high",
    "tone": "warm"
  },
  {
    "id": "asset_041",
    "title": "The Ritual of Ayurveda \u2014 Shower Foam (LANDING / DE)",
    "body": "The Shower Foam from The Ritual of Ayurveda invites you to slow down, breathe deeply, and embrace the art of self-care.",
    "asset_type": "landing",
    "collection": "The Ritual of Ayurveda",
    "product": "Shower Foam",
    "ritual_occasion": "replenishment",
    "audience": "new",
    "channel": "landing",
    "market": "DE",
    "language": "de",
    "approval_status": "approved",
    "master_asset_id": "asset_040",
    "performance_tag": "high",
    "tone": "informative"
  },
  {
    "id": "asset_042",
    "title": "The Ritual of Namaste \u2014 Face Oil (SOCIAL / UK)",
    "body": "Rediscover balance with The Ritual of Namaste. The Face Oil is inspired by ancient wisdom and crafted for modern life.",
    "asset_type": "social",
    "collection": "The Ritual of Namaste",
    "product": "Face Oil",
    "ritual_occasion": "self-care",
    "audience": "reactivation",
    "channel": "social",
    "market": "UK",
    "language": "en",
    "approval_status": "approved",
    "master_asset_id": "asset_040",
    "performance_tag": "medium",
    "tone": "luxury"
  },
  {
    "id": "asset_043",
    "title": "The Ritual of Sakura \u2014 Bath Salt (ALL / all)",
    "body": "Give the gift of ritual. The The Ritual of Sakura Bath Salt makes every moment a celebration of calm and beauty.",
    "asset_type": "email",
    "collection": "The Ritual of Sakura",
    "product": "Bath Salt",
    "ritual_occasion": "gifting",
    "audience": "all",
    "channel": "all",
    "market": "all",
    "language": "en",
    "approval_status": "pending",
    "master_asset_id": "asset_040",
    "performance_tag": "low",
    "tone": "warm"
  },
  {
    "id": "asset_044",
    "title": "The Ritual of Ayurveda \u2014 Candle (EMAIL / NL)",
    "body": "Your skin deserves the best. The Candle from The Ritual of Ayurveda is formulated with natural ingredients for a luxurious daily ritual.",
    "asset_type": "email",
    "collection": "The Ritual of Ayurveda",
    "product": "Candle",
    "ritual_occasion": "replenishment",
    "audience": "loyalty",
    "channel": "email",
    "market": "NL",
    "language": "nl",
    "approval_status": "expired",
    "master_asset_id": "asset_040",
    "performance_tag": "high",
    "tone": "informative"
  },
  {
    "id": "asset_045",
    "title": "The Ritual of Namaste \u2014 Body Cream (LANDING / DE)",
    "body": "Immerse yourself in the The Ritual of Namaste experience. Our Body Cream is crafted to transform your daily routine into a mindful ritual.",
    "asset_type": "landing",
    "collection": "The Ritual of Namaste",
    "product": "Body Cream",
    "ritual_occasion": "self-care",
    "audience": "new",
    "channel": "landing",
    "market": "DE",
    "language": "de",
    "approval_status": "approved",
    "master_asset_id": null,
    "performance_tag": "high",
    "tone": "luxury"
  },
  {
    "id": "asset_046",
    "title": "The Ritual of Sakura \u2014 Shower Foam (SOCIAL / UK)",
    "body": "The Shower Foam from The Ritual of Sakura invites you to slow down, breathe deeply, and embrace the art of self-care.",
    "asset_type": "social",
    "collection": "The Ritual of Sakura",
    "product": "Shower Foam",
    "ritual_occasion": "gifting",
    "audience": "reactivation",
    "channel": "social",
    "market": "UK",
    "language": "en",
    "approval_status": "approved",
    "master_asset_id": "asset_045",
    "performance_tag": "medium",
    "tone": "warm"
  },
  {
    "id": "asset_047",
    "title": "The Ritual of Ayurveda \u2014 Face Oil (ALL / all)",
    "body": "Rediscover balance with The Ritual of Ayurveda. The Face Oil is inspired by ancient wisdom and crafted for modern life.",
    "asset_type": "email",
    "collection": "The Ritual of Ayurveda",
    "product": "Face Oil",
    "ritual_occasion": "replenishment",
    "audience": "all",
    "channel": "all",
    "market": "all",
    "language": "en",
    "approval_status": "approved",
    "master_asset_id": "asset_045",
    "performance_tag": "low",
    "tone": "informative"
  },
  {
    "id": "asset_048",
    "title": "The Ritual of Namaste \u2014 Bath Salt (EMAIL / NL)",
    "body": "Give the gift of ritual. The The Ritual of Namaste Bath Salt makes every moment a celebration of calm and beauty.",
    "asset_type": "email",
    "collection": "The Ritual of Namaste",
    "product": "Bath Salt",
    "ritual_occasion": "self-care",
    "audience": "loyalty",
    "channel": "email",
    "market": "NL",
    "language": "nl",
    "approval_status": "pending",
    "master_asset_id": "asset_045",
    "performance_tag": "high",
    "tone": "luxury"
  },
  {
    "id": "asset_049",
    "title": "The Ritual of Sakura \u2014 Candle (LANDING / DE)",
    "body": "Your skin deserves the best. The Candle from The Ritual of Sakura is formulated with natural ingredients for a luxurious daily ritual.",
    "asset_type": "landing",
    "collection": "The Ritual of Sakura",
    "product": "Candle",
    "ritual_occasion": "gifting",
    "audience": "new",
    "channel": "landing",
    "market": "DE",
    "language": "de",
    "approval_status": "expired",
    "master_asset_id": "asset_045",
    "performance_tag": "high",
    "tone": "warm"
  },
  {
    "id": "asset_050",
    "title": "The Ritual of Ayurveda \u2014 Body Cream (SOCIAL / UK)",
    "body": "Immerse yourself in the The Ritual of Ayurveda experience. Our Body Cream is crafted to transform your daily routine into a mindful ritual.",
    "asset_type": "social",
    "collection": "The Ritual of Ayurveda",
    "product": "Body Cream",
    "ritual_occasion": "replenishment",
    "audience": "reactivation",
    "channel": "social",
    "market": "UK",
    "language": "en",
    "approval_status": "approved",
    "master_asset_id": null,
    "performance_tag": "medium",
    "tone": "informative"
  },
  {
    "id": "asset_051",
    "title": "The Ritual of Namaste \u2014 Shower Foam (ALL / all)",
    "body": "The Shower Foam from The Ritual of Namaste invites you to slow down, breathe deeply, and embrace the art of self-care.",
    "asset_type": "email",
    "collection": "The Ritual of Namaste",
    "product": "Shower Foam",
    "ritual_occasion": "self-care",
    "audience": "all",
    "channel": "all",
    "market": "all",
    "language": "en",
    "approval_status": "approved",
    "master_asset_id": "asset_050",
    "performance_tag": "low",
    "tone": "luxury"
  },
  {
    "id": "asset_052",
    "title": "The Ritual of Sakura \u2014 Face Oil (EMAIL / NL)",
    "body": "Rediscover balance with The Ritual of Sakura. The Face Oil is inspired by ancient wisdom and crafted for modern life.",
    "asset_type": "email",
    "collection": "The Ritual of Sakura",
    "product": "Face Oil",
    "ritual_occasion": "gifting",
    "audience": "loyalty",
    "channel": "email",
    "market": "NL",
    "language": "nl",
    "approval_status": "approved",
    "master_asset_id": "asset_050",
    "performance_tag": "high",
    "tone": "warm"
  },
  {
    "id": "asset_053",
    "title": "The Ritual of Ayurveda \u2014 Bath Salt (LANDING / DE)",
    "body": "Give the gift of ritual. The The Ritual of Ayurveda Bath Salt makes every moment a celebration of calm and beauty.",
    "asset_type": "landing",
    "collection": "The Ritual of Ayurveda",
    "product": "Bath Salt",
    "ritual_occasion": "replenishment",
    "audience": "new",
    "channel": "landing",
    "market": "DE",
    "language": "de",
    "approval_status": "pending",
    "master_asset_id": "asset_050",
    "performance_tag": "high",
    "tone": "informative"
  },
  {
    "id": "asset_054",
    "title": "The Ritual of Namaste \u2014 Candle (SOCIAL / UK)",
    "body": "Your skin deserves the best. The Candle from The Ritual of Namaste is formulated with natural ingredients for a luxurious daily ritual.",
    "asset_type": "social",
    "collection": "The Ritual of Namaste",
    "product": "Candle",
    "ritual_occasion": "self-care",
    "audience": "reactivation",
    "channel": "social",
    "market": "UK",
    "language": "en",
    "approval_status": "expired",
    "master_asset_id": "asset_050",
    "performance_tag": "medium",
    "tone": "luxury"
  },
  {
    "id": "asset_055",
    "title": "The Ritual of Sakura \u2014 Body Cream (ALL / all)",
    "body": "Immerse yourself in the The Ritual of Sakura experience. Our Body Cream is crafted to transform your daily routine into a mindful ritual.",
    "asset_type": "email",
    "collection": "The Ritual of Sakura",
    "product": "Body Cream",
    "ritual_occasion": "gifting",
    "audience": "all",
    "channel": "all",
    "market": "all",
    "language": "en",
    "approval_status": "approved",
    "master_asset_id": null,
    "performance_tag": "low",
    "tone": "warm"
  },
  {
    "id": "asset_056",
    "title": "The Ritual of Ayurveda \u2014 Shower Foam (EMAIL / NL)",
    "body": "The Shower Foam from The Ritual of Ayurveda invites you to slow down, breathe deeply, and embrace the art of self-care.",
    "asset_type": "email",
    "collection": "The Ritual of Ayurveda",
    "product": "Shower Foam",
    "ritual_occasion": "replenishment",
    "audience": "loyalty",
    "channel": "email",
    "market": "NL",
    "language": "nl",
    "approval_status": "approved",
    "master_asset_id": "asset_055",
    "performance_tag": "high",
    "tone": "informative"
  },
  {
    "id": "asset_057",
    "title": "The Ritual of Namaste \u2014 Face Oil (LANDING / DE)",
    "body": "Rediscover balance with The Ritual of Namaste. The Face Oil is inspired by ancient wisdom and crafted for modern life.",
    "asset_type": "landing",
    "collection": "The Ritual of Namaste",
    "product": "Face Oil",
    "ritual_occasion": "self-care",
    "audience": "new",
    "channel": "landing",
    "market": "DE",
    "language": "de",
    "approval_status": "approved",
    "master_asset_id": "asset_055",
    "performance_tag": "high",
    "tone": "luxury"
  },
  {
    "id": "asset_058",
    "title": "The Ritual of Sakura \u2014 Bath Salt (SOCIAL / UK)",
    "body": "Give the gift of ritual. The The Ritual of Sakura Bath Salt makes every moment a celebration of calm and beauty.",
    "asset_type": "social",
    "collection": "The Ritual of Sakura",
    "product": "Bath Salt",
    "ritual_occasion": "gifting",
    "audience": "reactivation",
    "channel": "social",
    "market": "UK",
    "language": "en",
    "approval_status": "pending",
    "master_asset_id": "asset_055",
    "performance_tag": "medium",
    "tone": "warm"
  },
  {
    "id": "asset_059",
    "title": "The Ritual of Ayurveda \u2014 Candle (ALL / all)",
    "body": "Your skin deserves the best. The Candle from The Ritual of Ayurveda is formulated with natural ingredients for a luxurious daily ritual.",
    "asset_type": "email",
    "collection": "The Ritual of Ayurveda",
    "product": "Candle",
    "ritual_occasion": "replenishment",
    "audience": "all",
    "channel": "all",
    "market": "all",
    "language": "en",
    "approval_status": "expired",
    "master_asset_id": "asset_055",
    "performance_tag": "low",
    "tone": "informative"
  },
  {
    "id": "asset_060",
    "title": "The Ritual of Namaste \u2014 Body Cream (EMAIL / NL)",
    "body": "Immerse yourself in the The Ritual of Namaste experience. Our Body Cream is crafted to transform your daily routine into a mindful ritual.",
    "asset_type": "email",
    "collection": "The Ritual of Namaste",
    "product": "Body Cream",
    "ritual_occasion": "self-care",
    "audience": "loyalty",
    "channel": "email",
    "market": "NL",
    "language": "nl",
    "approval_status": "approved",
    "master_asset_id": null,
    "performance_tag": "high",
    "tone": "luxury"
  },
  {
    "id": "asset_061",
    "title": "The Ritual of Sakura \u2014 Shower Foam (LANDING / DE)",
    "body": "The Shower Foam from The Ritual of Sakura invites you to slow down, breathe deeply, and embrace the art of self-care.",
    "asset_type": "landing",
    "collection": "The Ritual of Sakura",
    "product": "Shower Foam",
    "ritual_occasion": "gifting",
    "audience": "new",
    "channel": "landing",
    "market": "DE",
    "language": "de",
    "approval_status": "approved",
    "master_asset_id": "asset_060",
    "performance_tag": "high",
    "tone": "warm"
  },
  {
    "id": "asset_062",
    "title": "The Ritual of Ayurveda \u2014 Face Oil (SOCIAL / UK)",
    "body": "Rediscover balance with The Ritual of Ayurveda. The Face Oil is inspired by ancient wisdom and crafted for modern life.",
    "asset_type": "social",
    "collection": "The Ritual of Ayurveda",
    "product": "Face Oil",
    "ritual_occasion": "replenishment",
    "audience": "reactivation",
    "channel": "social",
    "market": "UK",
    "language": "en",
    "approval_status": "approved",
    "master_asset_id": "asset_060",
    "performance_tag": "medium",
    "tone": "informative"
  },
  {
    "id": "asset_063",
    "title": "The Ritual of Namaste \u2014 Bath Salt (ALL / all)",
    "body": "Give the gift of ritual. The The Ritual of Namaste Bath Salt makes every moment a celebration of calm and beauty.",
    "asset_type": "email",
    "collection": "The Ritual of Namaste",
    "product": "Bath Salt",
    "ritual_occasion": "self-care",
    "audience": "all",
    "channel": "all",
    "market": "all",
    "language": "en",
    "approval_status": "pending",
    "master_asset_id": "asset_060",
    "performance_tag": "low",
    "tone": "luxury"
  },
  {
    "id": "asset_064",
    "title": "The Ritual of Sakura \u2014 Candle (EMAIL / NL)",
    "body": "Your skin deserves the best. The Candle from The Ritual of Sakura is formulated with natural ingredients for a luxurious daily ritual.",
    "asset_type": "email",
    "collection": "The Ritual of Sakura",
    "product": "Candle",
    "ritual_occasion": "gifting",
    "audience": "loyalty",
    "channel": "email",
    "market": "NL",
    "language": "nl",
    "approval_status": "expired",
    "master_asset_id": "asset_060",
    "performance_tag": "high",
    "tone": "warm"
  },
  {
    "id": "asset_065",
    "title": "The Ritual of Ayurveda \u2014 Body Cream (LANDING / DE)",
    "body": "Immerse yourself in the The Ritual of Ayurveda experience. Our Body Cream is crafted to transform your daily routine into a mindful ritual.",
    "asset_type": "landing",
    "collection": "The Ritual of Ayurveda",
    "product": "Body Cream",
    "ritual_occasion": "replenishment",
    "audience": "new",
    "channel": "landing",
    "market": "DE",
    "language": "de",
    "approval_status": "approved",
    "master_asset_id": null,
    "performance_tag": "high",
    "tone": "informative"
  },
  {
    "id": "asset_066",
    "title": "The Ritual of Namaste \u2014 Shower Foam (SOCIAL / UK)",
    "body": "The Shower Foam from The Ritual of Namaste invites you to slow down, breathe deeply, and embrace the art of self-care.",
    "asset_type": "social",
    "collection": "The Ritual of Namaste",
    "product": "Shower Foam",
    "ritual_occasion": "self-care",
    "audience": "reactivation",
    "channel": "social",
    "market": "UK",
    "language": "en",
    "approval_status": "approved",
    "master_asset_id": "asset_065",
    "performance_tag": "medium",
    "tone": "luxury"
  },
  {
    "id": "asset_067",
    "title": "The Ritual of Sakura \u2014 Face Oil (ALL / all)",
    "body": "Rediscover balance with The Ritual of Sakura. The Face Oil is inspired by ancient wisdom and crafted for modern life.",
    "asset_type": "email",
    "collection": "The Ritual of Sakura",
    "product": "Face Oil",
    "ritual_occasion": "gifting",
    "audience": "all",
    "channel": "all",
    "market": "all",
    "language": "en",
    "approval_status": "approved",
    "master_asset_id": "asset_065",
    "performance_tag": "low",
    "tone": "warm"
  },
  {
    "id": "asset_068",
    "title": "The Ritual of Ayurveda \u2014 Bath Salt (EMAIL / NL)",
    "body": "Give the gift of ritual. The The Ritual of Ayurveda Bath Salt makes every moment a celebration of calm and beauty.",
    "asset_type": "email",
    "collection": "The Ritual of Ayurveda",
    "product": "Bath Salt",
    "ritual_occasion": "replenishment",
    "audience": "loyalty",
    "channel": "email",
    "market": "NL",
    "language": "nl",
    "approval_status": "pending",
    "master_asset_id": "asset_065",
    "performance_tag": "high",
    "tone": "informative"
  },
  {
    "id": "asset_069",
    "title": "The Ritual of Namaste \u2014 Candle (LANDING / DE)",
    "body": "Your skin deserves the best. The Candle from The Ritual of Namaste is formulated with natural ingredients for a luxurious daily ritual.",
    "asset_type": "landing",
    "collection": "The Ritual of Namaste",
    "product": "Candle",
    "ritual_occasion": "self-care",
    "audience": "new",
    "channel": "landing",
    "market": "DE",
    "language": "de",
    "approval_status": "expired",
    "master_asset_id": "asset_065",
    "performance_tag": "high",
    "tone": "luxury"
  },
  {
    "id": "asset_070",
    "title": "The Ritual of Sakura \u2014 Body Cream (SOCIAL / UK)",
    "body": "Immerse yourself in the The Ritual of Sakura experience. Our Body Cream is crafted to transform your daily routine into a mindful ritual.",
    "asset_type": "social",
    "collection": "The Ritual of Sakura",
    "product": "Body Cream",
    "ritual_occasion": "gifting",
    "audience": "reactivation",
    "channel": "social",
    "market": "UK",
    "language": "en",
    "approval_status": "approved",
    "master_asset_id": null,
    "performance_tag": "medium",
    "tone": "warm"
  },
  {
    "id": "asset_071",
    "title": "The Ritual of Ayurveda \u2014 Shower Foam (ALL / all)",
    "body": "The Shower Foam from The Ritual of Ayurveda invites you to slow down, breathe deeply, and embrace the art of self-care.",
    "asset_type": "email",
    "collection": "The Ritual of Ayurveda",
    "product": "Shower Foam",
    "ritual_occasion": "replenishment",
    "audience": "all",
    "channel": "all",
    "market": "all",
    "language": "en",
    "approval_status": "approved",
    "master_asset_id": "asset_070",
    "performance_tag": "low",
    "tone": "informative"
  },
  {
    "id": "asset_072",
    "title": "The Ritual of Namaste \u2014 Face Oil (EMAIL / NL)",
    "body": "Rediscover balance with The Ritual of Namaste. The Face Oil is inspired by ancient wisdom and crafted for modern life.",
    "asset_type": "email",
    "collection": "The Ritual of Namaste",
    "product": "Face Oil",
    "ritual_occasion": "self-care",
    "audience": "loyalty",
    "channel": "email",
    "market": "NL",
    "language": "nl",
    "approval_status": "approved",
    "master_asset_id": "asset_070",
    "performance_tag": "high",
    "tone": "luxury"
  },
  {
    "id": "asset_073",
    "title": "The Ritual of Sakura \u2014 Bath Salt (LANDING / DE)",
    "body": "Give the gift of ritual. The The Ritual of Sakura Bath Salt makes every moment a celebration of calm and beauty.",
    "asset_type": "landing",
    "collection": "The Ritual of Sakura",
    "product": "Bath Salt",
    "ritual_occasion": "gifting",
    "audience": "new",
    "channel": "landing",
    "market": "DE",
    "language": "de",
    "approval_status": "pending",
    "master_asset_id": "asset_070",
    "performance_tag": "high",
    "tone": "warm"
  },
  {
    "id": "asset_074",
    "title": "The Ritual of Ayurveda \u2014 Candle (SOCIAL / UK)",
    "body": "Your skin deserves the best. The Candle from The Ritual of Ayurveda is formulated with natural ingredients for a luxurious daily ritual.",
    "asset_type": "social",
    "collection": "The Ritual of Ayurveda",
    "product": "Candle",
    "ritual_occasion": "replenishment",
    "audience": "reactivation",
    "channel": "social",
    "market": "UK",
    "language": "en",
    "approval_status": "expired",
    "master_asset_id": "asset_070",
    "performance_tag": "medium",
    "tone": "informative"
  },
  {
    "id": "asset_075",
    "title": "The Ritual of Namaste \u2014 Body Cream (ALL / all)",
    "body": "Immerse yourself in the The Ritual of Namaste experience. Our Body Cream is crafted to transform your daily routine into a mindful ritual.",
    "asset_type": "email",
    "collection": "The Ritual of Namaste",
    "product": "Body Cream",
    "ritual_occasion": "self-care",
    "audience": "all",
    "channel": "all",
    "market": "all",
    "language": "en",
    "approval_status": "approved",
    "master_asset_id": null,
    "performance_tag": "low",
    "tone": "luxury"
  },
  {
    "id": "asset_076",
    "title": "The Ritual of Sakura \u2014 Shower Foam (EMAIL / NL)",
    "body": "The Shower Foam from The Ritual of Sakura invites you to slow down, breathe deeply, and embrace the art of self-care.",
    "asset_type": "email",
    "collection": "The Ritual of Sakura",
    "product": "Shower Foam",
    "ritual_occasion": "gifting",
    "audience": "loyalty",
    "channel": "email",
    "market": "NL",
    "language": "nl",
    "approval_status": "approved",
    "master_asset_id": "asset_075",
    "performance_tag": "high",
    "tone": "warm"
  },
  {
    "id": "asset_077",
    "title": "The Ritual of Ayurveda \u2014 Face Oil (LANDING / DE)",
    "body": "Rediscover balance with The Ritual of Ayurveda. The Face Oil is inspired by ancient wisdom and crafted for modern life.",
    "asset_type": "landing",
    "collection": "The Ritual of Ayurveda",
    "product": "Face Oil",
    "ritual_occasion": "replenishment",
    "audience": "new",
    "channel": "landing",
    "market": "DE",
    "language": "de",
    "approval_status": "approved",
    "master_asset_id": "asset_075",
    "performance_tag": "high",
    "tone": "informative"
  },
  {
    "id": "asset_078",
    "title": "The Ritual of Namaste \u2014 Bath Salt (SOCIAL / UK)",
    "body": "Give the gift of ritual. The The Ritual of Namaste Bath Salt makes every moment a celebration of calm and beauty.",
    "asset_type": "social",
    "collection": "The Ritual of Namaste",
    "product": "Bath Salt",
    "ritual_occasion": "self-care",
    "audience": "reactivation",
    "channel": "social",
    "market": "UK",
    "language": "en",
    "approval_status": "pending",
    "master_asset_id": "asset_075",
    "performance_tag": "medium",
    "tone": "luxury"
  },
  {
    "id": "asset_079",
    "title": "The Ritual of Sakura \u2014 Candle (ALL / all)",
    "body": "Your skin deserves the best. The Candle from The Ritual of Sakura is formulated with natural ingredients for a luxurious daily ritual.",
    "asset_type": "email",
    "collection": "The Ritual of Sakura",
    "product": "Candle",
    "ritual_occasion": "gifting",
    "audience": "all",
    "channel": "all",
    "market": "all",
    "language": "en",
    "approval_status": "expired",
    "master_asset_id": "asset_075",
    "performance_tag": "low",
    "tone": "warm"
  }
]